minette/__init__.py
minette/config.py
minette/core.py
minette/serializer.py
minette/utils.py
minette/version.py
minette/adapter/__init__.py
minette/adapter/base.py
minette/adapter/clovaadapter.py
minette/adapter/lineadapter.py
minette/datastore/__init__.py
minette/datastore/azurestoragestores.py
minette/datastore/connectionprovider.py
minette/datastore/contextstore.py
minette/datastore/messagelogstore.py
minette/datastore/mysqlstores.py
minette/datastore/sqlalchemystores.py
minette/datastore/sqldbstores.py
minette/datastore/sqlitestores.py
minette/datastore/storeset.py
minette/datastore/userstore.py
minette/dialog/__init__.py
minette/dialog/dependency.py
minette/dialog/router.py
minette/dialog/service.py
minette/models/__init__.py
minette/models/context.py
minette/models/group.py
minette/models/message.py
minette/models/payload.py
minette/models/performance.py
minette/models/priority.py
minette/models/response.py
minette/models/topic.py
minette/models/user.py
minette/models/wordnode.py
minette/scheduler/__init__.py
minette/scheduler/base.py
minette/tagger/__init__.py
minette/tagger/base.py
minette/tagger/janometagger.py
minette/tagger/mecabservice.py
minette/tagger/mecabtagger.py
minette/testing/__init__.py
minette/testing/helper.py
minette-0.4.3.dist-info/LICENSE
minette-0.4.3.dist-info/METADATA
minette-0.4.3.dist-info/WHEEL
minette-0.4.3.dist-info/top_level.txt
minette-0.4.3.dist-info/RECORD
