Metadata-Version: 2.1
Name: minette
Version: 0.4.3
Summary: Minette is a minimal and extensible chatbot framework. It is extremely easy to develop and the architecture preventing to be spaghetti code enables you to scale up to complex chatbot.
Home-page: https://github.com/uezo/minette-python
Author: uezo
Author-email: uezo@uezo.net
Maintainer: uezo
Maintainer-email: uezo@uezo.net
License: Apache v2
Platform: UNKNOWN
Classifier: Programming Language :: Python :: 3
Requires-Dist: pytz
Requires-Dist: schedule
